drongo_app/__init__.py
drongo_app/app.py
drongo_app/mw.py
drongo_app/options.py
drongo_app/run.py
drongo_app/run_dev.py
drongo_app-1.0.0.dist-info/METADATA
drongo_app-1.0.0.dist-info/RECORD
drongo_app-1.0.0.dist-info/WHEEL
drongo_app-1.0.0.dist-info/top_level.txt
drongo_app-1.0.0.dist-info/zip-safe
