Metadata-Version: 2.1
Name: drongo-app
Version: 1.0.0
Summary: Drongo app loader.
Home-page: UNKNOWN
Author: Sattvik Chakravarthy
Author-email: sattvik@gmail.com
License: UNKNOWN
Platform: UNKNOWN
Classifier: Development Status :: 5 - Production/Stable
Classifier: Environment :: Console
Classifier: Environment :: Web Environment
Classifier: Intended Audience :: Developers
Classifier: License :: OSI Approved :: MIT License
Classifier: Operating System :: MacOS :: MacOS X
Classifier: Operating System :: Microsoft :: Windows
Classifier: Operating System :: POSIX
Classifier: Programming Language :: Python
Classifier: Topic :: Internet :: WWW/HTTP
